CHANGELOG.md
DCO
step_exec_lib/__init__.py
step_exec_lib/errors.py
step_exec_lib/steps.py
step_exec_lib/types.py
step_exec_lib/utils/__init__.py
step_exec_lib/utils/config.py
step_exec_lib/utils/files.py
step_exec_lib/utils/processes.py
step_exec_lib-0.4.2.dist-info/METADATA
step_exec_lib-0.4.2.dist-info/WHEEL
step_exec_lib-0.4.2.dist-info/licenses/LICENSE
step_exec_lib-0.4.2.dist-info/RECORD
