Metadata-Version: 2.4
Name: step-exec-lib
Version: 0.4.2
Summary: A library that helps execute pipeline of tasks using filters and simple composition
Project-URL: Repository, https://github.com/giantswarm/step-exec-lib
Author-email: Łukasz Piątkowski <lukasz@giantswarm.io>
License-Expression: Apache-2.0
License-File: LICENSE
Keywords: composition,steps
Classifier: Development Status :: 4 - Beta
Classifier: Intended Audience :: Developers
Classifier: License :: OSI Approved :: Apache Software License
Classifier: Operating System :: POSIX :: Linux
Classifier: Programming Language :: Python
Classifier: Programming Language :: Python :: 3
Classifier: Programming Language :: Python :: 3.10
Classifier: Programming Language :: Python :: 3.11
Classifier: Programming Language :: Python :: 3.12
Classifier: Programming Language :: Python :: 3.13
Classifier: Programming Language :: Python :: 3.14
Classifier: Programming Language :: Python :: Implementation :: CPython
Requires-Python: <4,>=3.10
Requires-Dist: configargparse<2,>=1.4.1
Requires-Dist: gitpython<4,>=3.1.41
Requires-Dist: semver<4,>=3.0.0
